wuddz_search_gui/search_gui.py
wuddz_search_gui/wudz-sgui.ico
wuddz_search_gui-1.0.4.dist-info/METADATA
wuddz_search_gui-1.0.4.dist-info/WHEEL
wuddz_search_gui-1.0.4.dist-info/entry_points.txt
wuddz_search_gui-1.0.4.dist-info/licenses/LICENSE
wuddz_search_gui-1.0.4.dist-info/RECORD
