Metadata-Version: 2.1
Name: wuddz-search-gui
Version: 1.0.4
Summary: Python File/Folder Explorer GUI Application, Search, Open, Save, Copy, Move, Rename, Delete, Parse & Archive (Encryption Optional)
Project-URL: Homepage, https://github.com/wuddz-devs/Wuddz-Search-Gui
Project-URL: Download, https://github.com/wuddz-devs/Wuddz-Search-Gui/releases/download/v1.0.4/wuddz-search-gui-1.0.4.zip
Author-email: Wuddz-Devs <wuddz_devs@protonmail.com>
License: MIT License
License-File: LICENSE
Keywords: archive,copy,explorer,file,folder,gui,move,parse,search
Classifier: License :: OSI Approved :: MIT License
Classifier: Programming Language :: Python
Classifier: Programming Language :: Python :: 3.7
Classifier: Programming Language :: Python :: 3.8
Classifier: Programming Language :: Python :: 3.9
Classifier: Programming Language :: Python :: 3.10
Requires-Python: >=3.7
Requires-Dist: pyqt5>=5.15.7
